generate_background_image/__init__.py
generate_background_image/generate_background_image.py
generate_background_image-0.0.2.dist-info/LICENSE
generate_background_image-0.0.2.dist-info/METADATA
generate_background_image-0.0.2.dist-info/WHEEL
generate_background_image-0.0.2.dist-info/top_level.txt
generate_background_image-0.0.2.dist-info/RECORD
