Metadata-Version: 2.1
Name: generate-background-image
Version: 0.0.2
Summary: Generate a background image of words in a given string using the wordcloud module.
Home-page: https://github.com/mohdsaqibhbi/How-to-build-Python-Package.git
Author: Mohd Saqib
Author-email: mohdsaqibhbi@gmail.com
License: MIT
Download-URL: https://pypi.org/project/generate_background_image/
Keywords: generate image,background image,image for blog,image for git repo
Platform: UNKNOWN
Requires-Dist: wordcloud
